xqute/__init__.py
xqute/defaults.py
xqute/job.py
xqute/path.py
xqute/plugin.py
xqute/py.typed
xqute/scheduler.py
xqute/schedulers/__init__.py
xqute/schedulers/container_scheduler.py
xqute/schedulers/gbatch_scheduler.py
xqute/schedulers/local_scheduler.py
xqute/schedulers/sge_scheduler.py
xqute/schedulers/slurm_scheduler.py
xqute/schedulers/ssh_scheduler/__init__.py
xqute/schedulers/ssh_scheduler/client.py
xqute/schedulers/ssh_scheduler/scheduler.py
xqute/schedulers/ssh_scheduler/submitter.py
xqute/utils.py
xqute/xqute.py
xqute-2.0.6.dist-info/METADATA
xqute-2.0.6.dist-info/WHEEL
xqute-2.0.6.dist-info/licenses/LICENSE
xqute-2.0.6.dist-info/RECORD
