Metadata-Version: 2.4
Name: xqute
Version: 2.0.6
Summary: A job management system for python
License: MIT
License-File: LICENSE
Author: pwwang
Author-email: pwwang@pwwang.com
Requires-Python: >=3.9,<4.0
Classifier: License :: OSI Approved :: MIT License
Classifier: Programming Language :: Python :: 3
Classifier: Programming Language :: Python :: 3.9
Classifier: Programming Language :: Python :: 3.10
Classifier: Programming Language :: Python :: 3.11
Classifier: Programming Language :: Python :: 3.12
Classifier: Programming Language :: Python :: 3.13
Classifier: Programming Language :: Python :: 3.14
Provides-Extra: cloudsh
Provides-Extra: gcs
Provides-Extra: gs
Requires-Dist: aiofiles (>=23.0.0)
Requires-Dist: argx (>=0.4,<0.5)
Requires-Dist: cloudsh (>=0.3,<0.4) ; extra == "cloudsh"
Requires-Dist: gcloud-aio-storage (>=8.0.0) ; extra == "gcs" or extra == "gs"
Requires-Dist: panpath (>=0.4,<0.5)
Requires-Dist: rich (>=14,<15)
Requires-Dist: simplug (>=0.5,<0.6)
Requires-Dist: uvloop (>=0,<1)
Project-URL: Homepage, https://github.com/pwwang/xqute
Project-URL: Repository, https://github.com/pwwang/xqute
